faker/__init__.py
fakername-0.0.1.dist-info/METADATA
fakername-0.0.1.dist-info/WHEEL
fakername-0.0.1.dist-info/top_level.txt
fakername-0.0.1.dist-info/RECORD
