Metadata-Version: 2.1
Name: fakername
Version: 0.0.1
Summary: This project provides some test data names
Author: RTT
Author-email: 2835836810@qq.com
